README.rst
setup.py
Potion_client.egg-info/PKG-INFO
Potion_client.egg-info/SOURCES.txt
Potion_client.egg-info/dependency_links.txt
Potion_client.egg-info/pbr.json
Potion_client.egg-info/requires.txt
Potion_client.egg-info/top_level.txt
potion_client/__init__.py
potion_client/auth.py
potion_client/collection.py
potion_client/converter.py
potion_client/exceptions.py
potion_client/links.py
potion_client/resource.py
potion_client/schema.py
potion_client/utils.py