Metadata-Version: 1.1
Name: Potion-client
Version: 2.5.1
Summary: A client for APIs written in Flask-Potion
Home-page: https://github.com/biosustain/potion-client
Author: Lars Schöning
Author-email: lays@biosustain.dtu.dk
License: MIT
Platform: UNKNOWN
Classifier: Development Status :: 4 - Beta
Classifier: Topic :: Internet
Classifier: Programming Language :: Python :: 2.7
Classifier: Programming Language :: Python :: 3
Classifier: Programming Language :: Python :: 3.3
Classifier: Programming Language :: Python :: 3.4
Classifier: Programming Language :: Python :: 3.5
Classifier: License :: OSI Approved :: MIT License
